[
  {
    "listing_id": "4dc9dd65b43fd686",
    "source": "facebook",
    "url": "https://www.facebook.com/groups/333022240594651/posts/2110946456135545/",
    "title": "צביקה בירן: צביקה בירן",
    "description": "צביקה בירן\n‏11 דקות\n \n·\nבלעדיות חדשה להשכרה!\nרחוב ארלוזורוב 22 רמת גן\nעמלת תיווך מופחתת: חצי חודש + מע\"מ בלבד\nדירת 3.5 חדרים, כ 108 מ\"ר, משופצת, יפה, מרווחת ומוארת במיוחד.\nממוקמת בקומה 1 מתוך 3, בבניין נעים עם מקלט.\nהדירה בנויה בצורה מצוינת ונוחה מאוד למגורים:\nבצד אחד של הדירה יש חדר שינה ענק, ולצידו חדר נוסף, מקלחת ושירותים.\nבצד השני יש חדר שינה נוסף עם מקלחת ושירותים.\nבמרכז הדירה סלון גדול באופֵן ספייס עם המטבח, שנותן תחושה פתוחה, נעימה ומודרנית.\n כ 108 מ\"ר\n משופצת ויפה\n סלון פתוח עם מטבח\n 2 מקלחות ושירותים\n חדר שינה ענק\n מזגן בכל חדר\n דוד חשמל\n 3 כיווני אוויר\n מוארת מאוד\n מקרר ותנור כיריים נשארים בדירה\n מקלט בבניין\nתשלומים שוטפים:\nארנונה: כ 980 ₪\nועד בית: כ 160 ₪\nכניסה: 1/8\nמחיר: 7,000 ₪ לחודש\nהמיקום פשוט מעולה:\nבלב רמת גן, דקה הליכה מצומת ביאליק, קריניצי וארלוזורוב.\nהכול ממש מתחת לבית: תחבורה ציבורית, קניות, מסעדות, בתי קפה ושירותים קהילתיים.\nדירה גדולה, משופצת ומוארת במיקום מרכזי במיוחד, עם חלוקה מצוינת שמתאימה למשפחה, זוג שצריך חדר עבודה, או שותפים שרוצים פרטיות ונוחות.\nלתיאום ביקור:\nצביקה ילין, רימקס פוקוס\n052-8144448 פחות\n+6\n7,000 ₪\n \n · רמת גן, TA\n‏‏ ‏‏‏להשכרה דירת 108מר משופצת ויפהפייה במרכז העיר לכניסה ב-1/8- רחוב ארלוזורוב 22 רמת גן‏\nהודעה\n\n\n\n\nכתיבת ציבורית...",
    "location": "רמת גן",
    "raw_text": "צביקה בירן\n‏11 דקות\n \n·\nבלעדיות חדשה להשכרה!\nרחוב ארלוזורוב 22 רמת גן\nעמלת תיווך מופחתת: חצי חודש + מע\"מ בלבד\nדירת 3.5 חדרים, כ 108 מ\"ר, משופצת, יפה, מרווחת ומוארת במיוחד.\nממוקמת בקומה 1 מתוך 3, בבניין נעים עם מקלט.\nהדירה בנויה בצורה מצוינת ונוחה מאוד למגורים:\nבצד אחד של הדירה יש חדר שינה ענק, ולצידו חדר נוסף, מקלחת ושירותים.\nבצד השני יש חדר שינה נוסף עם מקלחת ושירותים.\nבמרכז הדירה סלון גדול באופֵן ספייס עם המטבח, שנותן תחושה פתוחה, נעימה ומודרנית.\n כ 108 מ\"ר\n משופצת ויפה\n סלון פתוח עם מטבח\n 2 מקלחות ושירותים\n חדר שינה ענק\n מזגן בכל חדר\n דוד חשמל\n 3 כיווני אוויר\n מוארת מאוד\n מקרר ותנור כיריים נשארים בדירה\n מקלט בבניין\nתשלומים שוטפים:\nארנונה: כ 980 ₪\nועד בית: כ 160 ₪\nכניסה: 1/8\nמחיר: 7,000 ₪ לחודש\nהמיקום פשוט מעולה:\nבלב רמת גן, דקה הליכה מצומת ביאליק, קריניצי וארלוזורוב.\nהכול ממש מתחת לבית: תחבורה ציבורית, קניות, מסעדות, בתי קפה ושירותים קהילתיים.\nדירה גדולה, משופצת ומוארת במיקום מרכזי במיוחד, עם חלוקה מצוינת שמתאימה למשפחה, זוג שצריך חדר עבודה, או שותפים שרוצים פרטיות ונוחות.\nלתיאום ביקור:\nצביקה ילין, רימקס פוקוס\n052-8144448 פחות\n+6\n7,000 ₪\n \n · רמת גן, TA\n‏‏ ‏‏‏להשכרה דירת 108מר משופצת ויפהפייה במרכז העיר לכניסה ב-1/8- רחוב ארלוזורוב 22 רמת גן‏\nהודעה\n\n\n\n\nכתיבת ציבורית...",
    "images": "[]",
    "extracted_price": 7000,
    "extracted_bedrooms": 3,
    "extracted_location": "תל אביב",
    "extracted_neighborhood": "הצפון הישן",
    "has_broker_fee": 1,
    "attributes": "{\"has_parking\": null, \"has_balcony\": null, \"has_elevator\": null, \"has_ac\": true, \"floor_number\": 1, \"is_ground_floor\": false, \"is_high_floor\": false, \"is_renovated\": true, \"allows_pets\": null, \"suitable_for_roommates\": true, \"has_storage\": null, \"has_security\": null, \"near_public_transport\": true, \"near_beach\": null, \"is_furnished\": false, \"from_owner_direct\": false, \"roomies\": false, \"is_sublet\": false}",
    "area_matches": "{\"רמת גן\": true}",
    "bordering_areas": "{}",
    "posted_at": "2026-06-27T14:04:00.309861",
    "scraped_at": "2026-06-27T14:15:44.104108",
    "enriched_at": "2026-06-27 11:16:44",
    "roomies": 0,
    "extracted_street": "ארלוזורוב 22",
    "screenshots": "{\"post_screenshot\": \"data/screenshots/81dbf2c251afe7fecc39a3e5e602bdf6/post.png\", \"gallery_screenshots\": [\"data/screenshots/81dbf2c251afe7fecc39a3e5e602bdf6/gallery_0.png\", \"data/screenshots/81dbf2c251afe7fecc39a3e5e602bdf6/gallery_1.png\", \"data/screenshots/81dbf2c251afe7fecc39a3e5e602bdf6/gallery_2.png\", \"data/screenshots/81dbf2c251afe7fecc39a3e5e602bdf6/gallery_3.png\", \"data/screenshots/81dbf2c251afe7fecc39a3e5e602bdf6/gallery_4.png\"]}",
    "is_sublet": 0,
    "sublet_duration": null,
    "sublet_dates": null,
    "extracted_size": 108,
    "phone": "052-8144448"
  }
]